product_category/__init__.py
product_category/pc_model.py
product_category/predict.py
product_category/train.py
product_category-0.0.2.dist-info/METADATA
product_category-0.0.2.dist-info/WHEEL
product_category-0.0.2.dist-info/top_level.txt
product_category-0.0.2.dist-info/RECORD
