Metadata-Version: 2.1
Name: product-category
Version: 0.0.2
Summary: Predicting product categories.
Home-page: https://github.com/yang-zhang/product_category
Author: Yang Zhang
Author-email: yang.zhang.ds@gmail.com
License: UNKNOWN
Platform: UNKNOWN
Classifier: Intended Audience :: Developers
Classifier: Intended Audience :: Science/Research
Classifier: Operating System :: OS Independent
Classifier: Programming Language :: Python
Classifier: Programming Language :: Python :: 3
Classifier: Topic :: Software Development :: Libraries
Classifier: Topic :: Software Development :: Libraries :: Python Modules
Requires-Dist: torch (==1.7.1)
Requires-Dist: transformers (==4.3.3)
Requires-Dist: pytorch-lightning (==1.2.1)
Requires-Dist: scikit-learn (==0.24.1)
Requires-Dist: black (==20.8b1)
Requires-Dist: pre-commit (==2.10.1)
Provides-Extra: test
Requires-Dist: pytest ; extra == 'test'
